taskgen/__init__.py
taskgen/cli.py
taskgen/core/__init__.py
taskgen/core/beam_generator.py
taskgen/core/beam_plotter.py
taskgen/core/beam_solver.py
taskgen/core/config.py
taskgen/core/description_pdf_generator.py
taskgen/core/orchestrator.py
taskgen/core/orchestrator_adapter.py
taskgen/core/plane2d_generator.py
taskgen/core/plane2d_plotter.py
taskgen/core/plane2d_solver.py
taskgen/data/properties.json
taskgen/docker/entrypoint.sh
taskgen/templates/beam_template.tex
taskgen/templates/plane2d_template.tex
structural_fem_taskgen_cli-0.1.7.dist-info/METADATA
structural_fem_taskgen_cli-0.1.7.dist-info/WHEEL
structural_fem_taskgen_cli-0.1.7.dist-info/entry_points.txt
structural_fem_taskgen_cli-0.1.7.dist-info/licenses/LICENSE
structural_fem_taskgen_cli-0.1.7.dist-info/RECORD
