Metadata-Version: 2.4
Name: structural-fem-taskgen-cli
Version: 0.1.7
Summary: Structural FEM task generator and solver
Project-URL: Repository, https://github.com/lukpacho/structural-fem-taskgen
Author-email: Lukasz Pachocki <pachockilukasz@gmail.com>
License: MIT License
License-File: LICENSE
Classifier: License :: OSI Approved :: MIT License
Classifier: Programming Language :: Python :: 3 :: Only
Classifier: Programming Language :: Python :: 3.11
Classifier: Programming Language :: Python :: 3.12
Requires-Python: >=3.11
Requires-Dist: adjusttext>=1.3.0
Requires-Dist: calfem-python>=3.6.8
Requires-Dist: gmsh>=4.13.1
Requires-Dist: jinja2>=3.1.4
Requires-Dist: matplotlib>=3.9.0
Requires-Dist: numpy>=1.26.4
Requires-Dist: platformdirs>=4.3.8
Requires-Dist: typer>=0.16.0
Provides-Extra: dev
Requires-Dist: black; extra == 'dev'
Requires-Dist: build; extra == 'dev'
Requires-Dist: mypy; extra == 'dev'
Requires-Dist: pre-commit; extra == 'dev'
Requires-Dist: pytest; extra == 'dev'
Requires-Dist: ruff; extra == 'dev'
Requires-Dist: twine; extra == 'dev'
